dbcAnalyzer/__init__.py
dbcAnalyzer/dbc.py
dbcAnalyzer-0.0.1.dist-info/LICENSE
dbcAnalyzer-0.0.1.dist-info/METADATA
dbcAnalyzer-0.0.1.dist-info/WHEEL
dbcAnalyzer-0.0.1.dist-info/top_level.txt
dbcAnalyzer-0.0.1.dist-info/RECORD
