Metadata-Version: 2.1
Name: dbcAnalyzer
Version: 0.0.1
Summary: A small tool for analysis dbc files
Author-email: LeeBai李白 <815921545@qq.com>
License: MIT License        
Project-URL: Homepage, https://github.com/LiBaiNotDrink
Project-URL: Bug Tracker, https://github.com/LiBaiNotDrink
Classifier: Programming Language :: Python :: 3
Classifier: License :: OSI Approved :: MIT License
Classifier: Operating System :: OS Independent
Requires-Python: >=3.7
License-File: LICENSE
